README.md
setup.py
termtime/__main__.py
termtime.egg-info/PKG-INFO
termtime.egg-info/SOURCES.txt
termtime.egg-info/dependency_links.txt
termtime.egg-info/entry_points.txt
termtime.egg-info/top_level.txt
termtime/fonts/__init__.py
termtime/fonts/default.py
termtime/modes/__init__.py
termtime/modes/clock.py
termtime/modes/countdown.py
termtime/modes/mode.py
termtime/modes/stopwatch.py