Metadata-Version: 1.1
Name: termtime
Version: 0.2.2
Summary: Stopwatch, Timer, Clock - All in the terminal
Home-page: https://github.com/vimist/termtime
Author: Vimist
Author-email: UNKNOWN
License: UNKNOWN
Keywords: terminal timer clock stopwatch
Platform: UNKNOWN
Classifier: Environment :: Console
Classifier: Natural Language :: English
Classifier: Intended Audience :: Developers
Classifier: Intended Audience :: Information Technology
Classifier: Intended Audience :: System Administrators
